resulty/__init__.py
resulty/core.py
resulty/wraps.py
resulty-0.1.1.dist-info/METADATA
resulty-0.1.1.dist-info/WHEEL
resulty-0.1.1.dist-info/licenses/LICENSE
resulty-0.1.1.dist-info/RECORD
