Metadata-Version: 2.3
Name: resulty
Version: 0.1.1
Summary: A rust like Result type for Python
Author-email: Rémi Kalbe <me@remi.boo>
License-File: LICENSE
Classifier: Development Status :: 3 - Alpha
Classifier: Intended Audience :: Developers
Classifier: License :: OSI Approved :: MIT License
Classifier: Operating System :: OS Independent
Classifier: Programming Language :: Python :: 3
Classifier: Programming Language :: Python :: 3.12
Classifier: Typing :: Typed
Requires-Python: <3.13,>=3.12
